watz/__init__.py
watz/_client_base.py
watz/client.py
watz/helpers.py
watz/models.py
watz/py.typed
watz/_endpoints/__init__.py
watz/_endpoints/_endpoint.py
watz/_endpoints/activity_create.py
watz/_endpoints/ping.py
watz/_endpoints/req_base.py
watz/_endpoints/resp_base.py
watz/_endpoints/subject_create.py
watz/_endpoints/subject_list.py
watz/_endpoints/trace_create.py
watz/_endpoints/trace_data.py
watz/_endpoints/trace_list.py
watz-0.1.0.dist-info/METADATA
watz-0.1.0.dist-info/WHEEL
watz-0.1.0.dist-info/licenses/LICENSE.md
watz-0.1.0.dist-info/RECORD
