Metadata-Version: 2.1
Name: watz
Version: 0.1.0
Summary: Python SDK for Watz APIs
Project-URL: Sourcecode, https://github.com/watz-inc/watz-py
Project-URL: Documentation, https://watz-inc.github.io/watz-py
Author-email: Watz Inc <zak@watz.coach>
License: Apache-2.0
License-File: LICENSE.md
Classifier: Development Status :: 3 - Alpha
Classifier: License :: OSI Approved
Classifier: Programming Language :: Python
Classifier: Programming Language :: Python :: 3
Classifier: Programming Language :: Python :: 3 :: Only
Classifier: Programming Language :: Python :: 3.9
Classifier: Programming Language :: Python :: 3.10
Classifier: Programming Language :: Python :: 3.11
Classifier: Programming Language :: Python :: 3.12
Requires-Python: <3.13,>=3.9
Requires-Dist: anyio<4.0.0,>=3.5.0
Requires-Dist: httpx>=0.23.1
Requires-Dist: orjson>=3.8.0
Requires-Dist: pydantic!=2.4.0,!=2.4.1,<3.0.0,>=2.2.0
